click_params/__init__.py
click_params/annotations.py
click_params/base.py
click_params/domain.py
click_params/miscellaneous.py
click_params/network.py
click_params/numeric.py
click_params/test_utils.py
click_params-0.5.0.dist-info/LICENSE
click_params-0.5.0.dist-info/METADATA
click_params-0.5.0.dist-info/WHEEL
click_params-0.5.0.dist-info/RECORD
