Metadata-Version: 2.1
Name: click-params
Version: 0.5.0
Summary: A bunch of useful click parameter types
Home-page: https://click-params.readthedocs.io/en/stable
License: Apache-2.0
Keywords: click,params,validators,network,cli
Author: lewoudar
Author-email: lewoudar@gmail.com
Requires-Python: >=3.8.1,<4.0.0
Classifier: Intended Audience :: Developers
Classifier: License :: OSI Approved :: Apache Software License
Classifier: Operating System :: OS Independent
Classifier: Programming Language :: Python :: 3
Classifier: Programming Language :: Python :: 3.9
Classifier: Programming Language :: Python :: 3.10
Classifier: Programming Language :: Python :: 3.11
Classifier: Programming Language :: Python :: Implementation :: PyPy
Classifier: Topic :: Terminals
Requires-Dist: click (>=7.0,<9.0)
Requires-Dist: deprecated (>=1.2.14,<2.0.0)
Requires-Dist: validators (>=0.22,<0.23)
Project-URL: Bug Tracker, https://github.com/click-contrib/click_params/issues
Project-URL: Documentation, https://click-params.readthedocs.io/en/stable
Project-URL: Repository, https://github.com/click-contrib/click_params
